<doctrine-mapping
    xmlns="http://doctrine-project.org/schemas/phpcr-odm/phpcr-mapping"
    xmlns:xsi="http://www.w3.org/2001/XMLSchema-instance"
    xsi:schemaLocation="http://doctrine-project.org/schemas/phpcr-odm/phpcr-mapping
    https://github.com/doctrine/phpcr-odm/raw/master/doctrine-phpcr-odm-mapping.xsd"
    >

    <document
        name="Symfony\Cmf\Bundle\MediaBundle\Doctrine\Phpcr\Directory"
        node-type="nt:folder"
        >

        <mixins>
            <mixin type="mix:lastModified" />
        </mixins>

        <id name="id">
            <generator strategy="PARENT"/>
        </id>
        <nodename name="name"/>
        <parent-document name="parent"/>

        <children name="children"/>

        <field name="createdAt" type="date" property="jcr:created"/>
        <field name="updatedAt" type="date" property="jcr:lastModified"/>

    </document>

</doctrine-mapping>
